logtalk_jupyter_kernel-0.46.0.dist-info/licenses/LICENSE
logtalk_kernel/__init__.py
logtalk_kernel/__main__.py
logtalk_kernel/install.py
logtalk_kernel/kernel.py
logtalk_kernel/logtalk_kernel_base_implementation.py
logtalk_kernel/logtalk_kernel_config.py
logtalk_kernel/sicstus_kernel_implementation.py
logtalk_kernel/swi_kernel_implementation.py
logtalk_kernel/kernelspec/logo-32x32.png
logtalk_kernel/kernelspec/logo-64x64.png
logtalk_kernel/kernelspec/logo-svg.svg
logtalk_kernel/logtalk_server/jupyter.lgt
logtalk_kernel/logtalk_server/jupyter_forms.lgt
logtalk_kernel/logtalk_server/jupyter_inputs.lgt
logtalk_kernel/logtalk_server/jupyter_jsonrpc.lgt
logtalk_kernel/logtalk_server/jupyter_logging.lgt
logtalk_kernel/logtalk_server/jupyter_preferences.lgt
logtalk_kernel/logtalk_server/jupyter_query_handling.lgt
logtalk_kernel/logtalk_server/jupyter_request_handling.lgt
logtalk_kernel/logtalk_server/jupyter_server.lgt
logtalk_kernel/logtalk_server/jupyter_term_handling.lgt
logtalk_kernel/logtalk_server/jupyter_variable_bindings.lgt
logtalk_kernel/logtalk_server/jupyter_widgets.lgt
logtalk_kernel/logtalk_server/loader.lgt
logtalk_jupyter_kernel-0.46.0.dist-info/METADATA
logtalk_jupyter_kernel-0.46.0.dist-info/WHEEL
logtalk_jupyter_kernel-0.46.0.dist-info/top_level.txt
logtalk_jupyter_kernel-0.46.0.dist-info/RECORD
