Metadata-Version: 2.4
Name: logtalk-jupyter-kernel
Version: 0.46.0
Summary: Hercutalk - A Jupyter Kernel for Logtalk
Author: Paulo Moura, Anne Brecklinghaus, Michael Leuschel, dgelessus
Maintainer-email: Paulo Moura <pmoura@logtalk.org>
License-Expression: MIT
Project-URL: Source, https://github.com/LogtalkDotOrg/logtalk-jupyter-kernel
Project-URL: Issues, https://github.com/LogtalkDotOrg/logtalk-jupyter-kernel/issues
Keywords: logtalk,prolog,logic-programming
Classifier: Development Status :: 4 - Beta
Classifier: Framework :: Jupyter
Classifier: Operating System :: OS Independent
Classifier: Intended Audience :: Developers
Classifier: Intended Audience :: Education
Classifier: Topic :: Scientific/Engineering
Classifier: Topic :: System :: Shells
Classifier: Natural Language :: English
Classifier: Programming Language :: Prolog
Requires-Python: >=3.7
License-File: LICENSE
Requires-Dist: jupyter_client
Requires-Dist: IPython
Requires-Dist: ipykernel
Requires-Dist: jupytext
Requires-Dist: graphviz
Requires-Dist: beautifulsoup4
Requires-Dist: matplotlib
Provides-Extra: dev
Requires-Dist: jupyter_core; extra == "dev"
Requires-Dist: jupyterlab; extra == "dev"
Requires-Dist: notebook; extra == "dev"
Dynamic: license-file
